pearmut/app.py
pearmut/assignment.py
pearmut/cli.py
pearmut/constants.py
pearmut/results_export.py
pearmut/utils.py
pearmut/static/annotate.bundle.js
pearmut/static/annotate.html
pearmut/static/dashboard.bundle.js
pearmut/static/dashboard.html
pearmut/static/favicon.svg
pearmut/static/index.bundle.js
pearmut/static/index.html
pearmut/static/style.css
pearmut-1.0.2.dist-info/licenses/LICENSE
pearmut-1.0.2.dist-info/METADATA
pearmut-1.0.2.dist-info/WHEEL
pearmut-1.0.2.dist-info/entry_points.txt
pearmut-1.0.2.dist-info/top_level.txt
pearmut-1.0.2.dist-info/RECORD
