Metadata-Version: 2.4
Name: pearmut
Version: 1.0.2
Summary: A tool for evaluation of model outputs, primarily MT.
Author-email: Vilém Zouhar <vilem.zouhar@gmail.com>
License: MIT
Project-URL: Repository, https://github.com/zouharvi/pearmut
Project-URL: Issues, https://github.com/zouharvi/pearmut/issues
Keywords: evaluation,machine translation,human evaluation,annotation
Requires-Python: >=3.12
License-File: LICENSE
Requires-Dist: fastapi>=0.110.0
Requires-Dist: uvicorn>=0.29.0
Requires-Dist: wonderwords>=3.0.0
Requires-Dist: psutil>=7.1.0
Requires-Dist: typst>=0.14.4
Provides-Extra: dev
Requires-Dist: pytest; extra == "dev"
Dynamic: license-file
